zn_operation_table/__init__.py
zn_operation_table/zn_operation_table.py
zn_operation_table-1.1.5.dist-info/LICENSE
zn_operation_table-1.1.5.dist-info/METADATA
zn_operation_table-1.1.5.dist-info/WHEEL
zn_operation_table-1.1.5.dist-info/top_level.txt
zn_operation_table-1.1.5.dist-info/RECORD
