Metadata-Version: 2.1
Name: zn-operation-table
Version: 1.1.5
Summary: Simple package to obtain Zn's equivalence classes sum or product operation tables.
Home-page: https://github.com/JuanpiCasti/zn_operation_table_generator
Author: Juan Pablo Castiglione
Author-email: juanpablocastiglione01@gmail.com
License: UNKNOWN
Project-URL: Bug Tracker, https://github.com/JuanpiCasti/zn_operation_table_generator/issues
Platform: UNKNOWN
Classifier: Programming Language :: Python :: 3
Classifier: License :: OSI Approved :: MIT License
Classifier: Operating System :: OS Independent
Requires-Python: >=3.6
License-File: LICENSE
